valmix/__init__.py
valmix/app.py
valmix/knob.py
valmix/knob_widget.py
valmix/run.py
valmix-1.0.0.dist-info/licenses/LICENSE
valmix-1.0.0.dist-info/WHEEL
valmix-1.0.0.dist-info/METADATA
valmix-1.0.0.dist-info/RECORD
