Metadata-Version: 2.4
Name: valmix
Version: 1.0.0
Summary: Adjust numerical values from a terminal user interface.
Keywords: multiprocessing,value,tui,user,interface
Author-email: Stéphane Caron <stephane.caron@inria.fr>
Maintainer-email: Stéphane Caron <stephane.caron@inria.fr>
Requires-Python: >=3.8
Classifier: Development Status :: 5 - Production/Stable
Classifier: Environment :: Console
Classifier: Intended Audience :: Developers
Classifier: Intended Audience :: Science/Research
Classifier: License :: OSI Approved :: Apache Software License
Classifier: Operating System :: POSIX :: Linux
Classifier: Programming Language :: Python :: 3.8
Classifier: Programming Language :: Python :: 3.9
Classifier: Programming Language :: Python :: 3.10
Classifier: Programming Language :: Python :: 3.11
Classifier: Programming Language :: Python :: 3.12
Classifier: Typing :: Typed
License-File: LICENSE
Requires-Dist: textual >=0.57.1
Project-URL: Changelog, https://github.com/stephane-caron/valmix/blob/main/CHANGELOG.md
Project-URL: Homepage, https://github.com/stephane-caron/valmix
Project-URL: Source, https://github.com/stephane-caron/valmix
Project-URL: Tracker, https://github.com/stephane-caron/valmix/issues
